aliyunsdktag/__init__.py
aliyunsdktag/endpoint.py
aliyunsdktag/request/__init__.py
aliyunsdktag/request/v20180828/AttachPolicyRequest.py
aliyunsdktag/request/v20180828/CheckCreatedByEnabledRequest.py
aliyunsdktag/request/v20180828/CloseCreatedByRequest.py
aliyunsdktag/request/v20180828/CreatePolicyRequest.py
aliyunsdktag/request/v20180828/CreateTagsRequest.py
aliyunsdktag/request/v20180828/DeletePolicyRequest.py
aliyunsdktag/request/v20180828/DeleteTagRequest.py
aliyunsdktag/request/v20180828/DescribeRegionsRequest.py
aliyunsdktag/request/v20180828/DetachPolicyRequest.py
aliyunsdktag/request/v20180828/DisablePolicyTypeRequest.py
aliyunsdktag/request/v20180828/EnablePolicyTypeRequest.py
aliyunsdktag/request/v20180828/GenerateConfigRuleReportRequest.py
aliyunsdktag/request/v20180828/GetConfigRuleReportRequest.py
aliyunsdktag/request/v20180828/GetEffectivePolicyRequest.py
aliyunsdktag/request/v20180828/GetPolicyEnableStatusRequest.py
aliyunsdktag/request/v20180828/GetPolicyRequest.py
aliyunsdktag/request/v20180828/ListConfigRulesForTargetRequest.py
aliyunsdktag/request/v20180828/ListPoliciesForTargetRequest.py
aliyunsdktag/request/v20180828/ListPoliciesRequest.py
aliyunsdktag/request/v20180828/ListResourcesByTagRequest.py
aliyunsdktag/request/v20180828/ListSupportResourceTypesRequest.py
aliyunsdktag/request/v20180828/ListTagKeysRequest.py
aliyunsdktag/request/v20180828/ListTagResourcesRequest.py
aliyunsdktag/request/v20180828/ListTagValuesRequest.py
aliyunsdktag/request/v20180828/ListTargetsForPolicyRequest.py
aliyunsdktag/request/v20180828/ModifyPolicyRequest.py
aliyunsdktag/request/v20180828/OpenCreatedByRequest.py
aliyunsdktag/request/v20180828/TagResourcesRequest.py
aliyunsdktag/request/v20180828/UntagResourcesRequest.py
aliyunsdktag/request/v20180828/__init__.py
aliyun_python_sdk_tag-1.0.6.dist-info/LICENSE
aliyun_python_sdk_tag-1.0.6.dist-info/METADATA
aliyun_python_sdk_tag-1.0.6.dist-info/WHEEL
aliyun_python_sdk_tag-1.0.6.dist-info/top_level.txt
aliyun_python_sdk_tag-1.0.6.dist-info/RECORD
